flask_misaka.py
Flask_Misaka-1.0.1.dist-info/AUTHORS
Flask_Misaka-1.0.1.dist-info/LICENSE
Flask_Misaka-1.0.1.dist-info/METADATA
Flask_Misaka-1.0.1.dist-info/WHEEL
Flask_Misaka-1.0.1.dist-info/top_level.txt
Flask_Misaka-1.0.1.dist-info/RECORD
